{"x":1038.7817511236,"width":2205.35414481163,"y":-584.272069605723,"items":[{"rotation":0,"x":1045.98,"width":0,"isContour":false,"y":90.87,"holder":false,"holderIndex":-1,"height":13.85,"points":[[1045.98,90.87],[1045.98,104.72]]},{"rotation":0,"x":1159.37,"width":0,"isContour":false,"y":90.87,"holder":false,"holderIndex":-1,"height":13.85,"points":[[1159.37,104.72],[1159.37,90.87]]},{"rotation":0,"x":1654.02,"width":0,"isContour":false,"y":344.41,"holder":false,"holderIndex":-1,"height":7.09,"points":[[1654.02,351.5],[1654.02,344.41]]},{"rotation":0,"x":551.34,"width":0,"isContour":false,"y":344.41,"holder":false,"holderIndex":-1,"height":7.09,"points":[[551.34,351.5],[551.34,344.41]]},{"rotation":0,"x":1102.68,"width":0,"isContour":false,"y":344.41,"holder":false,"holderIndex":-1,"height":7.09,"points":[[1102.68,351.5],[1102.68,344.41]]},{"rotation":0,"x":1654.02,"width":0,"isContour":false,"y":0,"holder":false,"holderIndex":-1,"height":7.09,"points":[[1654.02,7.09],[1654.02,0]]},{"rotation":0,"x":551.34,"width":0,"isContour":false,"y":0,"holder":false,"holderIndex":-1,"height":7.09,"points":[[551.34,7.09],[551.34,0]]},{"rotation":0,"x":1102.68,"width":0,"isContour":false,"y":0,"holder":false,"holderIndex":-1,"height":7.09,"points":[[1102.68,7.09],[1102.68,0]]},{"rotation":0,"x":0,"width":2205.35,"isContour":true,"y":0,"holder":false,"holderIndex":-1,"height":351.5,"points":[[2205.35,0],[2205.35,175.75],[2205.35,351.5],[1102.68,351.5],[0,351.5],[0,175.75],[0,0],[1102.68,0]],"segments":[[[0.0,0.0],[1102.68,0.0],[2205.35,0.0]],[[2205.35,0.0],[2205.35,175.75],[2205.35,351.5]],[[2205.35,351.5],[1102.68,351.5],[0.0,351.5]],[[0.0,351.5],[0.0,175.75],[0.0,0.0]]],"centroid":[1102.677072405815,175.7480316162105]}],"height":351.496063232421}