{"x":-2441.33094083776,"width":3741.73228346457,"y":532.745474544656,"items":[{"rotation":0,"x":0,"width":3741.73,"isContour":true,"y":0,"holder":false,"holderIndex":-1,"height":340.42,"points":[[3741.73,0],[3741.73,340.42],[1870.87,340.42],[0,340.42],[0,0],[1870.87,0]],"segments":[[[0.0,0.0],[1870.87,0.0],[3741.73,0.0]],[[3741.73,0.0],[3741.73,340.42]],[[3741.73,340.42],[1870.87,340.42],[0.0,340.42]],[[0.0,340.42],[0.0,0.0]]],"centroid":[1870.866141732285,170.21142578125]},{"rotation":0,"x":1813.47,"width":0,"isContour":false,"y":243.24,"holder":false,"holderIndex":-1,"height":9.38,"points":[[1813.47,252.62],[1813.47,243.24]]},{"rotation":0,"x":1928.26,"width":0,"isContour":false,"y":243.24,"holder":false,"holderIndex":-1,"height":9.38,"points":[[1928.26,243.24],[1928.26,252.62]]},{"rotation":0,"x":1870.87,"width":0,"isContour":false,"y":331.65,"holder":false,"holderIndex":-1,"height":8.78,"points":[[1870.87,340.42],[1870.87,331.65]]},{"rotation":0,"x":1870.87,"width":0,"isContour":false,"y":0,"holder":false,"holderIndex":-1,"height":8.75,"points":[[1870.87,8.75],[1870.87,0]]},{"rotation":0,"x":23.43,"width":3695.18,"isContour":false,"y":24.14,"holder":false,"holderIndex":-1,"height":292.12,"points":[[3718.61,24.14],[3718.61,316.26],[1870.87,316.26],[23.43,316.26],[23.43,24.14],[1870.87,24.14]],"segments":[[[23.43,24.14],[1870.87,24.14],[3718.61,24.14]],[[3718.61,24.14],[3718.61,316.26]],[[3718.61,316.26],[1870.87,316.26],[23.43,316.26]],[[23.43,316.26],[23.43,24.14]]],"isSewing":true},{"rotation":0,"x":942.64,"width":8.29,"isContour":false,"y":331.16,"holder":false,"holderIndex":-1,"height":0,"points":[[942.64,331.16],[950.93,331.16]]},{"rotation":0,"x":946.79,"width":0,"isContour":false,"y":331.16,"holder":false,"holderIndex":-1,"height":8.52,"points":[[946.79,339.68],[946.79,331.16]]},{"rotation":0,"x":942.64,"width":8.29,"isContour":false,"y":7.78,"holder":false,"holderIndex":-1,"height":0,"points":[[950.93,7.78],[942.64,7.78]]},{"rotation":0,"x":946.79,"width":0,"isContour":false,"y":-0.74,"holder":false,"holderIndex":-1,"height":8.52,"points":[[946.79,-0.74],[946.79,7.78]]},{"rotation":0,"x":2789.16,"width":8.29,"isContour":false,"y":331.9,"holder":false,"holderIndex":-1,"height":0,"points":[[2789.16,331.9],[2797.45,331.9]]},{"rotation":0,"x":2793.3,"width":0,"isContour":false,"y":331.9,"holder":false,"holderIndex":-1,"height":8.52,"points":[[2793.3,340.42],[2793.3,331.9]]},{"rotation":0,"x":2789.16,"width":8.29,"isContour":false,"y":8.52,"holder":false,"holderIndex":-1,"height":0,"points":[[2797.45,8.52],[2789.16,8.52]]},{"rotation":0,"x":2793.3,"width":0,"isContour":false,"y":0,"holder":false,"holderIndex":-1,"height":8.52,"points":[[2793.3,0],[2793.3,8.52]]}],"height":340.4228515625}