{
  "x": 3414.3990858503894,
  "width": 1409.1,
  "y": -2490.92235837941,
  "items": [
    {
      "isGuides": false,
      "rotation": 0.0,
      "width": 1409.1,
      "x": 0.0,
      "isContour": true,
      "y": 0.0,
      "points": [
        [
          10.0,
          0.0
        ],
        [
          10.0,
          0.804698034206231
        ],
        [
          4.999006458022851,
          0.804698034206231
        ],
        [
          0.0,
          0.804698034206231
        ],
        [
          0.0,
          0.0
        ],
        [
          4.999006458022851,
          0.0
        ]
      ],
      "height": 113.39,
      "segments": [
        [
          [
            0.0,
            0.0
          ],
          [
            4.999006458022851,
            0.0
          ],
          [
            10.0,
            0.0
          ]
        ],
        [
          [
            10.0,
            0.0
          ],
          [
            10.0,
            0.804698034206231
          ]
        ],
        [
          [
            10.0,
            0.804698034206231
          ],
          [
            4.999006458022851,
            0.804698034206231
          ],
          [
            0.0,
            0.804698034206231
          ]
        ],
        [
          [
            0.0,
            0.804698034206231
          ],
          [
            0.0,
            0.0
          ]
        ]
      ],
      "centroid": [
        704.55,
        56.695
      ]
    }
  ],
  "height": 113.39
}
