{
  "x": 1112.2155965047205,
  "width": 1283.53,
  "y": -720.8784874301291,
  "items": [
    {
      "isGuides": false,
      "rotation": 0.0,
      "width": 1283.53,
      "x": 0.0,
      "isContour": true,
      "y": 0.0,
      "points": [
        [
          0.4999961044930777,
          0.0
        ],
        [
          1.0,
          0.0
        ],
        [
          0.9693034054521515,
          0.0518959432190911
        ],
        [
          0.9991118244217121,
          0.10379967745202683
        ],
        [
          0.4999961044930777,
          0.10379967745202683
        ],
        [
          0.0011063239659376875,
          0.10379967745202683
        ],
        [
          0.03069659454784851,
          0.0518959432190911
        ],
        [
          0.0,
          0.0
        ]
      ],
      "height": 133.23,
      "segments": [
        [
          [
            0.0,
            0.0
          ],
          [
            0.4999961044930777,
            0.0
          ],
          [
            0.4999961044930777,
            0.0
          ],
          [
            1.0,
            0.0
          ]
        ],
        [
          [
            1.0,
            0.0
          ],
          [
            0.9693034054521515,
            0.0518959432190911
          ]
        ],
        [
          [
            0.9693034054521515,
            0.0518959432190911
          ],
          [
            0.9991118244217121,
            0.10379967745202683
          ]
        ],
        [
          [
            0.9991118244217121,
            0.10379967745202683
          ],
          [
            0.4999961044930777,
            0.10379967745202683
          ],
          [
            0.0011063239659376875,
            0.10379967745202683
          ]
        ],
        [
          [
            0.0011063239659376875,
            0.10379967745202683
          ],
          [
            0.03069659454784851,
            0.0518959432190911
          ]
        ],
        [
          [
            0.03069659454784851,
            0.0518959432190911
          ],
          [
            0.0,
            0.0
          ]
        ]
      ],
      "centroid": [
        641.765,
        66.615
      ]
    },
    {
      "isGuides": true,
      "rotation": 0.0,
      "width": 1203.87,
      "x": 39.97,
      "isContour": false,
      "y": 22.68,
      "points": [
        [
          0.4999961044930777,
          0.017670019399624474
        ],
        [
          0.9690774660506571,
          0.017670019399624474
        ],
        [
          0.9487585019438579,
          0.051677794831441415
        ],
        [
          0.9686411692753578,
          0.08612965805240236
        ],
        [
          0.4999961044930777,
          0.08612965805240236
        ],
        [
          0.031584770126136516,
          0.08612965805240236
        ],
        [
          0.05123370704229742,
          0.051677794831441415
        ],
        [
          0.031140682336992513,
          0.017670019399624474
        ]
      ],
      "height": 87.87,
      "segments": [
        [
          [
            0.031140682336992513,
            0.017670019399624474
          ],
          [
            0.4999961044930777,
            0.017670019399624474
          ],
          [
            0.4999961044930777,
            0.017670019399624474
          ],
          [
            0.9690774660506571,
            0.017670019399624474
          ]
        ],
        [
          [
            0.9690774660506571,
            0.017670019399624474
          ],
          [
            0.9487585019438579,
            0.051677794831441415
          ]
        ],
        [
          [
            0.9487585019438579,
            0.051677794831441415
          ],
          [
            0.9686411692753578,
            0.08612965805240236
          ]
        ],
        [
          [
            0.9686411692753578,
            0.08612965805240236
          ],
          [
            0.4999961044930777,
            0.08612965805240236
          ],
          [
            0.031584770126136516,
            0.08612965805240236
          ]
        ],
        [
          [
            0.031584770126136516,
            0.08612965805240236
          ],
          [
            0.05123370704229742,
            0.051677794831441415
          ]
        ],
        [
          [
            0.05123370704229742,
            0.051677794831441415
          ],
          [
            0.031140682336992513,
            0.017670019399624474
          ]
        ]
      ],
      "isSewing": true
    },
    {
      "isGuides": false,
      "rotation": 0.0,
      "width": 0.0,
      "x": 641.76,
      "isContour": false,
      "y": 124.72,
      "points": [
        [
          0.4999961044930777,
          0.10379967745202683
        ],
        [
          0.4999961044930777,
          0.09716952467024534
        ]
      ],
      "height": 8.5
    }
  ],
  "height": 133.23
}
