{
  "x": 1487.7619420051597,
  "width": 1499.53,
  "y": -733.0566235188307,
  "items": [
    {
      "isGuides": true,
      "rotation": 0.0,
      "width": 1250.65,
      "x": 22.68,
      "isContour": false,
      "y": 22.68,
      "points": [
        [
          8.491460657672738,
          0.15124739084913272
        ],
        [
          8.491460657672738,
          0.7561702666835608
        ],
        [
          0.15124739084913272,
          0.7561702666835608
        ],
        [
          0.15124739084913272,
          0.15124739084913272
        ]
      ],
      "height": 90.71,
      "segments": [
        [
          [
            0.15124739084913272,
            0.15124739084913272
          ],
          [
            8.491460657672738,
            0.15124739084913272
          ]
        ],
        [
          [
            8.491460657672738,
            0.15124739084913272
          ],
          [
            8.491460657672738,
            0.7561702666835608
          ]
        ],
        [
          [
            8.491460657672738,
            0.7561702666835608
          ],
          [
            0.15124739084913272,
            0.7561702666835608
          ]
        ],
        [
          [
            0.15124739084913272,
            0.7561702666835608
          ],
          [
            0.15124739084913272,
            0.15124739084913272
          ]
        ]
      ],
      "isSewing": true
    },
    {
      "isGuides": false,
      "rotation": 0.0,
      "width": 1499.53,
      "x": 0.0,
      "isContour": true,
      "y": 0.0,
      "points": [
        [
          10.0,
          0.0
        ],
        [
          10.0,
          0.9073509699705907
        ],
        [
          0.0,
          0.9073509699705907
        ],
        [
          0.0,
          0.0
        ]
      ],
      "height": 136.06,
      "segments": [
        [
          [
            0.0,
            0.0
          ],
          [
            10.0,
            0.0
          ]
        ],
        [
          [
            10.0,
            0.0
          ],
          [
            10.0,
            0.9073509699705907
          ]
        ],
        [
          [
            10.0,
            0.9073509699705907
          ],
          [
            0.0,
            0.9073509699705907
          ]
        ],
        [
          [
            0.0,
            0.9073509699705907
          ],
          [
            0.0,
            0.0
          ]
        ]
      ],
      "centroid": [
        749.765,
        68.03
      ]
    },
    {
      "isGuides": false,
      "rotation": 0.0,
      "width": 0.0,
      "x": 1273.32,
      "isContour": false,
      "y": 126.97,
      "points": [
        [
          8.491460657672738,
          0.8467319760191527
        ],
        [
          8.491460657672738,
          0.8962141470994244
        ]
      ],
      "height": 7.42
    }
  ],
  "height": 136.06
}
