{
  "x": 2679.56729674429,
  "width": 552.755899999991,
  "y": -890.707578564372,
  "items": [
    {
      "rotation": 0,
      "x": 0,
      "width": 552.76,
      "isContour": true,
      "y": 0,
      "holder": false,
      "holderIndex": -1,
      "height": 99.21,
      "points": [
        [
          10.000074173790077,
          0.0
        ],
        [
          10.000074173790077,
          1.7948248042219288
        ],
        [
          0.0,
          1.7948248042219288
        ],
        [
          0.0,
          0.0
        ]
      ],
      "segments": [
        [
          [
            0.0,
            0.0
          ],
          [
            10.000074173790077,
            0.0
          ]
        ],
        [
          [
            10.000074173790077,
            0.0
          ],
          [
            10.000074173790077,
            1.7948248042219288
          ]
        ],
        [
          [
            10.000074173790077,
            1.7948248042219288
          ],
          [
            0.0,
            1.7948248042219288
          ]
        ],
        [
          [
            0.0,
            1.7948248042219288
          ],
          [
            0.0,
            0.0
          ]
        ]
      ],
      "centroid": [
        276.3779499999955,
        49.60630000000035
      ]
    }
  ],
  "height": 99.2126000000007
}
